confens/__init__.py
confens/classifiers/Classifier.py
confens/classifiers/ConfidenceBagging.py
confens/classifiers/ConfidenceBoosting.py
confens/classifiers/ConfidenceEnsemble.py
confens/classifiers/__init__.py
confens/examples/__init__.py
confens/examples/example_supervised.py
confens/examples/example_unsupervised.py
confens/examples/rq1-2.py
confens/examples/rq3.py
confens/metrics/DiversityMetric.py
confens/metrics/EnsembleMetric.py
confens/metrics/__init__.py
confens/tests/__init__.py
confens/tests/pyod_compatibility.py
confens/tests/sklearn_compatibility.py
confens/utils/__init__.py
confens/utils/classifier_utils.py
confens/utils/general_utils.py
confidence_ensembles-0.10.dist-info/licenses/LICENSE.txt
confidence_ensembles-0.10.dist-info/METADATA
confidence_ensembles-0.10.dist-info/WHEEL
confidence_ensembles-0.10.dist-info/top_level.txt
confidence_ensembles-0.10.dist-info/RECORD
