Metadata-Version: 2.4
Name: confidence-ensembles
Version: 0.10
Summary: Confidence Ensembles to Improve Classification
Home-page: https://github.com/tommyippoz/confidence-ensembles
Author: Tommaso Zoppi
Author-email: tommaso.zoppi@unifi.it
Keywords: machine learning,confidence,safety,ensemble
Classifier: Programming Language :: Python :: 3
Classifier: License :: OSI Approved :: MIT License
Classifier: Operating System :: OS Independent
License-File: LICENSE.txt
Dynamic: author
Dynamic: author-email
Dynamic: classifier
Dynamic: description
Dynamic: description-content-type
Dynamic: home-page
Dynamic: keywords
Dynamic: license-file
Dynamic: summary
